netapp_dataops/netapp_dataops_cli.py
netapp_dataops/mcp_server/config.py
netapp_dataops/mcp_server/netapp_dataops_ontap_mcp.py
netapp_dataops/traditional/__init__.py
netapp_dataops_traditional-2.6.0.data/scripts/netapp_dataops_cli.py
netapp_dataops_traditional-2.6.0.data/scripts/netapp_dataops_ontap_mcp.py
netapp_dataops_traditional-2.6.0.dist-info/licenses/LICENSE
netapp_dataops_traditional-2.6.0.dist-info/METADATA
netapp_dataops_traditional-2.6.0.dist-info/WHEEL
netapp_dataops_traditional-2.6.0.dist-info/top_level.txt
netapp_dataops_traditional-2.6.0.dist-info/RECORD
