Metadata-Version: 2.4
Name: netapp-dataops-traditional
Version: 2.6.0
Summary: NetApp DataOps Toolkit for Traditional Environments
Home-page: https://github.com/NetApp/netapp-data-science-toolkit/
Author: Mike Oglesby
Author-email: mike.oglesby@netapp.com
Maintainer: NetApp
Maintainer-email: ng-ai-inquiry@netapp.com
License: BSD-3-Clause
Project-URL: Bug Tracker, https://github.com/NetApp/netapp-data-science-toolkit/issues
Project-URL: Documentation, https://github.com/NetApp/netapp-data-science-toolkit/blob/main/README.md
Project-URL: Source Code, https://github.com/NetApp/netapp-data-science-toolkit/
Classifier: License :: OSI Approved :: BSD License
Classifier: Programming Language :: Python :: 3
Classifier: Programming Language :: Python :: 3.8
Classifier: Programming Language :: Python :: 3.9
Classifier: Programming Language :: Python :: 3.10
Classifier: Programming Language :: Python :: 3.11
Classifier: Programming Language :: Python :: 3.12
Classifier: Programming Language :: Python :: 3.13
Requires-Python: <3.14,>=3.8
License-File: LICENSE
Requires-Dist: netapp-ontap
Requires-Dist: pandas
Requires-Dist: tabulate
Requires-Dist: numpy>=1.22.0
Requires-Dist: requests
Requires-Dist: boto3
Requires-Dist: pyyaml
Requires-Dist: fastmcp
Dynamic: license-file
